<?xml version="1.0" encoding="UTF-8"?>
<xml><metadata><artist>Albert King</artist><title> I Believe To My Soul</title>
<songInfo><songwriter><name> 
Ray
Charles

</name></songwriter><recordDate>recording of July 1 1973, Jazz Festival Montreux,
Switzerland

</recordDate><album>from 
Live
at Montreux Blues at Sunrise (Stax or Fantasy
8546)
, 
</album></songInfo></metadata>
<lyrics>


<l>One of these days an' it won't be long, yeah

</l>
<l>You gonna look for me an' I'll be gone



</l>
<l>I believe, I say I believe right now

</l>
<l>Hey, hey, hey, baby

</l>
<l>You tryin' to make a fool of me, now



</l>
<l>You goin' 'round here with your head so hard, yeah

</l>
<l>I think I'm gonna have to use my rod



</l>
<l>I believe, I say I believe right now

</l>
<l>Hey, hey, hey, baby

</l>
<l>You tryin' to make a fool of me, now



</l>
<l>Now last night you were dreamin' when I heard you say, yeah

</l>
<l>"Ho Johnny", when you know my name is Ray



</l>
<l>I believe, I say I believe right now, yeah

</l>
<l>Woah-oh-oh, baby

</l>
<l>You're tryin' to make a fool of me, now



</l>
<l>Oh!



</l>
<l>You're gonna 'round here with your head so hard, yeah

</l>
<l>I think I'm gonna have to use my rod



</l>
<l>I believe, I say I believe right now, yeah

</l>
<l>Hey, hey, hey baby

</l>
<l>You're tryin' to make a fool of me now, hey



</l>
<l>Yeah!



</l>
<l>Thank you!

</l><l>Thank you very much!</l></lyrics></xml>