<?xml version="1.0" encoding="UTF-8"?>
<root>
    <title>Story Quest For <character>Arataki Itto</character> Walkthrough Guide</title>

    <date>Last Updated: 2021/12/14 07:11 </date>
    <p type="description"><character>Arataki Itto's</character>
        <constellation>Taurus Iracundus</constellation> Story Quest is an upcoming story Quest for
        version 2.3 of Genshin Impact. Learn how to unlock, walkthrough chart, release date, and
        more about <constellation>Taurus Iracundus</constellation>!</p>

    <subTitle><character>Arataki Itto</character> Story Quest - How To Unlock</subTitle>

    <header><character>Arataki Itto</character> Story Quest</header>

    <subHeader>A New Story Quest For 2.3 Update</subHeader>

    <front>Release Date</front>

    <end>
        <date alt="2021/12/14">December 14, 2021</date>
    </end>

    <front>Eligibility</front>

    <end>Adventure Rank 40 or above</end>

    <front>How To Unlock</front>

    <end>Complete the <quest>Omnipresence Over Mortals</quest></end>
    <end>Complete Chapter: <quest>Act I - "Dracaena Somnolenta Chapter</quest>" </end>
    <p type="description">Join <character>Arataki Itto</character> on his own story quest and get to
        know more of <character>Itto's</character> background as the descendant of the Crimson Oni.
        His story quest will be available permanently after the 2.3 game update. </p>
    <p>Requires 1 Story Key To Unlock</p>

    <p>Upon the release of the Story Quest, it's likely that it will require 1 story key to unlock
        it similar to previously released Story Quests.</p>

    <p>Get Story Keys By Doing Daily Commissions</p>

    <p>You can obtain Story Keys by doing daily commissions. You can keep a maximum amount of 3
        keys.</p>

    <header>Who Is <character>Arataki Itto</character>?</header>

    <subHeader>Oni of <location>Hanamizaka</location></subHeader>

    <p type="characterDescription">A new <region>Inazuma</region>
        <visionType>Geo</visionType> character that wields a <weaponType>Claymore</weaponType>
        weapon. He is the first and considered the greatest Head of the Arataki Gang and an intrepid
        man with Oni blood running through his veins.</p>

    <header><character>Arataki Itto</character> Story Quest - Walkthrough Chart and
        Location</header>

    <subHeader>Story Quest Start Location</subHeader>

    <p type="direction">Arataki Itto's story quest will start off by going to the
            <location>Adventurer's Guild</location> and talking to <character>Katheryne</character>
        of <region>Inazuma</region>. </p>
    <subheader><character>Arataki Itto</character> Story Quest</subheader>

    <p>Taurus Iracundus Chapter</p>

    <p step="1">Talk to <character>Katheryne</character> in <region>Inazuma</region></p>

    <p step="2">Talk to <character>Furuya Noboru</character></p>

    <p step="3">Talk to <character>Ogura Mio</character></p>

    <p step="4">Talk to <character>Uesugi</character></p>

    <p step="5">Talk to <character>Sango</character> Obtain: <questItem>A Bag of
        Beans</questItem></p>

    <p step="6">Go to <location>Yashiori Island</location> and search for <character>Arataki
            Itto</character> To Do: Use Elemental Sight and follow the foot trail</p>

    <p step="7">Throw beans at <character>Arataki Itto</character> Note: Avoid getting caught by
        him</p>

    <p step="8">Go to the <location>Onikabuto capture shot</location> (above the hill)</p>

    <p step="9">Go to <location>a certain tree around the area</location> and catch an Onikabuto
        with Itto</p>

    <p step="10">Go down to <location>the cliff</location> and go to <location>the next
            tree</location> to search for another Onikabuto</p>

    <p step="11">Go to a <location>certain rock</location>, where you will find (1) one
        Onikabuto</p>

    <p step="12">Go back <location>near the camp</location> and have a Bettle battle with
            <character>Daisuke</character> and <character>Itto</character></p>

    <p step="13">Go to <location>Fort Fujitou</location></p>

    <p step="14">Talk to <character>Masato</character></p>

    <p step="15">Go to <location>Nazuchi Beach</location></p>

    <p step="16">Defeat the enemies Character Trial: <character>Arataki Itto</character></p>

    <p step="17">Defeat the Tenryou Guards Character Trial: Arataki Itto</p>

    <p step="18">Follow the footprints in order to chase <character alias="blueOni"
            >Takuya</character> (Blue Oni)</p>

    <p step="19">Search for a <location>Hidden Hideout</location>.</p>

    <p step="20">Enter the domain and defeat the enemies Event Domain: Crumbling Guilt Character
        Trial: <character>Arataki Itto</character></p>

    <p step="21">Go back to <character>Grandma Oni</character></p>

    <subHeader>Obtain A <questItem>Bag Of Beans</questItem></subHeader>

    <p>After talking to <character>Sango</character>, she will give you A <questItem>Bag of
            Beans</questItem> that will be used in order to capture <character>Arataki
            Itto</character>. This item is only available on <character>Arataki Itto's</character>
        quest and its usage is still unknown.</p>

    <header><character>Arataki Itto</character> Story Quest - Rewards</header>

    <subHeader>Rewards List</subHeader>

    <li>
        <Exp kind="adventurerExp" amount="700">Exp</Exp>
    </li>
    <li>
        <item itemType="currency" currency="premium" amount="60" rarity="*****">Primogems</item>
    </li>
    <li>
        <item itemType="currency" currency="standard" amount="44000" rarity="***">Mora</item>
    </li>
    <li>
        <item itemType="talentMaterial" tier="II" amount="5" rarity="***">Guide To Elegance</item>
    </li>
    <li>
        <item itemType="characterExp" amount="5" tier="III" rarity="****">Hero's Wit</item>
    </li>
    <li>
        <item itemType="weaponExp" amount="10" tier="III" rarity="***">Mystic Enhancement Ore</item>
    </li>
</root>
